nr/__init__.py
nr/markdown.py
nr.markdown-1.0.7.dist-info/LICENSE.txt
nr.markdown-1.0.7.dist-info/METADATA
nr.markdown-1.0.7.dist-info/WHEEL
nr.markdown-1.0.7.dist-info/top_level.txt
nr.markdown-1.0.7.dist-info/zip-safe
nr.markdown-1.0.7.dist-info/RECORD
