Metadata-Version: 2.1
Name: nr.markdown
Version: 1.0.7
Summary: Extends the misaka Markdown parser and renderer for some nifty features.
Home-page: https://git.niklasrosenstein.com/NiklasRosenstein/nr
Author: Niklas Rosenstein
Author-email: rosensteinniklas@gmail.com
License: MIT
Platform: UNKNOWN
Requires-Python: >=3.4.0,<4.0.0
Requires-Dist: misaka (<3.0.0,>=2.1.1)
